inboxes_api/__init__.py
inboxes_api/__meta__.py
inboxes_api/client/__init__.py
inboxes_api/client/client.py
inboxes_api/client/session/__init__.py
inboxes_api/client/session/aiohttp.py
inboxes_api/client/session/base.py
inboxes_api/client/session/protocols.py
inboxes_api/types/__init__.py
inboxes_api/types/base.py
inboxes_api/types/message.py
inboxes_api/utils/__init__.py
inboxes_api/utils/headers.py
inboxes_api/utils/url_model.py
inboxes_api-0.1.0.dist-info/LICENSE
inboxes_api-0.1.0.dist-info/METADATA
inboxes_api-0.1.0.dist-info/WHEEL
inboxes_api-0.1.0.dist-info/RECORD
